flask_marshmallow_openapi/__init__.py
flask_marshmallow_openapi/flask_paths.py
flask_marshmallow_openapi/middleware.py
flask_marshmallow_openapi/py.typed
flask_marshmallow_openapi/schemas_registry.py
flask_marshmallow_openapi/securities.py
flask_marshmallow_openapi/static_collector.py
flask_marshmallow_openapi/decorators/__init__.py
flask_marshmallow_openapi/decorators/decorate_delete.py
flask_marshmallow_openapi/decorators/decorate_get.py
flask_marshmallow_openapi/decorators/decorate_patch.py
flask_marshmallow_openapi/decorators/decorate_post.py
flask_marshmallow_openapi/decorators/helpers.py
flask_marshmallow_openapi/static/redoc_favicon.png
flask_marshmallow_openapi/static/swagger_ui/favicon-16x16.png
flask_marshmallow_openapi/static/swagger_ui/favicon-32x32.png
flask_marshmallow_openapi/static/swagger_ui/index.css
flask_marshmallow_openapi/static/swagger_ui/index.html
flask_marshmallow_openapi/static/swagger_ui/oauth2-redirect.html
flask_marshmallow_openapi/static/swagger_ui/swagger-initializer.js
flask_marshmallow_openapi/static/swagger_ui/swagger-ui-bundle.js
flask_marshmallow_openapi/static/swagger_ui/swagger-ui-es-bundle-core.js
flask_marshmallow_openapi/static/swagger_ui/swagger-ui-es-bundle.js
flask_marshmallow_openapi/static/swagger_ui/swagger-ui-standalone-preset.js
flask_marshmallow_openapi/static/swagger_ui/swagger-ui.css
flask_marshmallow_openapi/static/swagger_ui/swagger-ui.js
flask_marshmallow_openapi/templates/changelog.html.jinja2
flask_marshmallow_openapi/templates/re_doc.jinja2
flask_marshmallow_openapi/templates/swagger_ui.jinja2
flask_marshmallow_openapi-0.6.9.dist-info/licenses/LICENSE
flask_marshmallow_openapi-0.6.9.dist-info/METADATA
flask_marshmallow_openapi-0.6.9.dist-info/WHEEL
flask_marshmallow_openapi-0.6.9.dist-info/top_level.txt
flask_marshmallow_openapi-0.6.9.dist-info/RECORD
