Metadata-Version: 2.4
Name: flask-marshmallow-openapi
Version: 0.6.9
Summary: Flask + marshmallow + OpenAPI
Author-email: Tomislav Adamic <tomislav.adamic@gmail.com>
License: MIT
Project-URL: Source, https://github.com/tadams42/flask-marshmallow-openapi
Project-URL: Documentation, https://flask-marshmallow-openapi.readthedocs.io/en/latest/
Keywords: OpenAPI SwaggerUI ReDoc
Platform: any
Classifier: Development Status :: 4 - Beta
Classifier: License :: OSI Approved :: MIT License
Classifier: Operating System :: POSIX :: Linux
Classifier: Programming Language :: Python
Classifier: Programming Language :: Python :: 3
Classifier: Programming Language :: Python :: 3.10
Classifier: Programming Language :: Python :: 3.11
Classifier: Programming Language :: Python :: 3.12
Classifier: Programming Language :: Python :: 3.13
Classifier: Programming Language :: Python :: 3 :: Only
Requires-Python: >=3.10
License-File: LICENSE
Requires-Dist: apispec[marshmallow,yaml]
Requires-Dist: flask>=2.0.1
Requires-Dist: inflection
Requires-Dist: marshmallow>=3.18.0
Requires-Dist: pyyaml
Requires-Dist: requests
Requires-Dist: wrapt
Requires-Dist: openapi-pydantic-models>=1.0.1
Provides-Extra: dev
Requires-Dist: black>=22.1.0; extra == "dev"
Requires-Dist: bump2version>=1.0.1; extra == "dev"
Requires-Dist: check-manifest>=0.47; extra == "dev"
Requires-Dist: flask-shell-ipython>=0.5.1; extra == "dev"
Requires-Dist: ipython>=8.6.0; extra == "dev"
Requires-Dist: pip-tools>=6.5.1; extra == "dev"
Requires-Dist: ruff; extra == "dev"
Requires-Dist: rich; extra == "dev"
Provides-Extra: docs
Requires-Dist: furo; extra == "docs"
Requires-Dist: myst-parser; extra == "docs"
Requires-Dist: sphinx>5.2.0; extra == "docs"
Requires-Dist: sphinx_rtd_theme; extra == "docs"
Requires-Dist: sphinx-copybutton; extra == "docs"
Provides-Extra: tests
Requires-Dist: coverage; extra == "tests"
Requires-Dist: factory-boy>=3.2.1; extra == "tests"
Requires-Dist: faker>=12.3.0; extra == "tests"
Requires-Dist: pytest>=7.0.1; extra == "tests"
Requires-Dist: pytest-spec>=3.2.0; extra == "tests"
Dynamic: license-file
